matoanko/__init__.py
matoanko/serial.py
matoanko-0.0.2.dist-info/METADATA
matoanko-0.0.2.dist-info/WHEEL
matoanko-0.0.2.dist-info/licenses/LICENSE
matoanko-0.0.2.dist-info/RECORD
