Metadata-Version: 2.1
Name: matoanko
Version: 0.0.2
Summary: python base libs
Project-URL: Homepage, https://github.com/sunlulu427/mato-anko
Project-URL: Bug Tracker, https://github.com/sunlulu427/mato-anko/issues
Author-email: "sunlulu.tomato" <sunlulu.tomato@bytedance.com>
License: Copyright (c) <2023> <copyright sunlulu.tomato@bytedance.com>
License-File: LICENSE
Classifier: License :: OSI Approved :: MIT License
Classifier: Operating System :: OS Independent
Classifier: Programming Language :: Python :: 3
Requires-Python: >=3.7
Requires-Dist: configparser; python_version >= '3.7'
